dohamaps/__init__.py
dohamaps/callbacks.py
dohamaps/const.py
dohamaps/data.py
dohamaps/img.py
dohamaps/inits.py
dohamaps/layers.py
dohamaps/losses.py
dohamaps/metrics.py
dohamaps/models.py
dohamaps/run.py
dohamaps/util.py
dohamaps-1.1.4.dist-info/LICENSE
dohamaps-1.1.4.dist-info/METADATA
dohamaps-1.1.4.dist-info/WHEEL
dohamaps-1.1.4.dist-info/top_level.txt
dohamaps-1.1.4.dist-info/RECORD
